dawnote/__init__.py
dawnote/_metadata.py
dawnote/_notes.py
dawnote/cli.py
dawnote/note.py
dawnote/notes.py
dawnote/paths.py
dawnote/utils.py
tests/__init__.py
tests/test_note.py
dawnote-0.0.1.dist-info/LICENSE
dawnote-0.0.1.dist-info/METADATA
dawnote-0.0.1.dist-info/WHEEL
dawnote-0.0.1.dist-info/entry_points.txt
dawnote-0.0.1.dist-info/top_level.txt
dawnote-0.0.1.dist-info/RECORD
